MANIFEST.in
README.md
requirements.txt
setup.py
src/yamlpyowl/__init__.py
src/yamlpyowl/core.py
src/yamlpyowl/old_core.py
src/yamlpyowl/release.py
src/yamlpyowl/script.py
src/yamlpyowl.egg-info/PKG-INFO
src/yamlpyowl.egg-info/SOURCES.txt
src/yamlpyowl.egg-info/dependency_links.txt
src/yamlpyowl.egg-info/entry_points.txt
src/yamlpyowl.egg-info/requires.txt
src/yamlpyowl.egg-info/top_level.txt